wujing/__init__.py
wujing/data/deduplicate.py
wujing/data/load_excel.py
wujing/data/split.py
wujing/data/tests/test_deduplicate.py
wujing/ml/__init__.py
wujing/ml/label_encoder.py
wujing/ml/stats.py
wujing/ml/tests/test_label_encoder.py
wujing/py.typed
wujing/rag/__init__.py
wujing/rag/bm25retriever.py
wujing/rag/embedder.py
wujing/rag/internal/fts/base_fts.py
wujing/rag/internal/fts/compare_fts.py
wujing/rag/internal/fts/duckdb_fts.py
wujing/rag/internal/fts/sqlite_fts.py
wujing/rag/internal/fts/tests/test_duckdb_fts.py
wujing/rag/internal/fts/tests/test_sqlite_fts.py
wujing/rag/internal/nltk_data/corpora/stopwords/README
wujing/rag/internal/nltk_data/corpora/stopwords/albanian
wujing/rag/internal/nltk_data/corpora/stopwords/arabic
wujing/rag/internal/nltk_data/corpora/stopwords/azerbaijani
wujing/rag/internal/nltk_data/corpora/stopwords/basque
wujing/rag/internal/nltk_data/corpora/stopwords/belarusian
wujing/rag/internal/nltk_data/corpora/stopwords/bengali
wujing/rag/internal/nltk_data/corpora/stopwords/catalan
wujing/rag/internal/nltk_data/corpora/stopwords/chinese
wujing/rag/internal/nltk_data/corpora/stopwords/danish
wujing/rag/internal/nltk_data/corpora/stopwords/dutch
wujing/rag/internal/nltk_data/corpora/stopwords/english
wujing/rag/internal/nltk_data/corpora/stopwords/finnish
wujing/rag/internal/nltk_data/corpora/stopwords/french
wujing/rag/internal/nltk_data/corpora/stopwords/german
wujing/rag/internal/nltk_data/corpora/stopwords/greek
wujing/rag/internal/nltk_data/corpora/stopwords/hebrew
wujing/rag/internal/nltk_data/corpora/stopwords/hinglish
wujing/rag/internal/nltk_data/corpora/stopwords/hungarian
wujing/rag/internal/nltk_data/corpora/stopwords/indonesian
wujing/rag/internal/nltk_data/corpora/stopwords/italian
wujing/rag/internal/nltk_data/corpora/stopwords/kazakh
wujing/rag/internal/nltk_data/corpora/stopwords/nepali
wujing/rag/internal/nltk_data/corpora/stopwords/norwegian
wujing/rag/internal/nltk_data/corpora/stopwords/portuguese
wujing-4.0.1.dist-info/WHEEL
wujing-4.0.1.dist-info/METADATA
wujing-4.0.1.dist-info/RECORD
