Metadata-Version: 2.3
Name: wujing
Version: 4.0.1
Summary: py-kit
Requires-Dist: adjusttext>=1
Requires-Dist: datasets>=2
Requires-Dist: openpyxl>=3
Requires-Dist: openai>=1.42.0
Requires-Dist: pandas>=1
Requires-Dist: mistune>=3.1.2
Requires-Dist: jieba>=0.42.1
Requires-Dist: nltk>=3.9.1
Requires-Dist: sentence-transformers>=4.0.2 ; extra == 'rag'
Requires-Dist: chromadb>=1.0.4 ; extra == 'rag'
Requires-Dist: chromadb>=1.0.15 ; extra == 'rag'
Requires-Dist: sqlalchemy>=2.0.41 ; extra == 'rag'
Requires-Dist: duckdb>=1.3.1 ; extra == 'rag'
Requires-Dist: duckdb-engine>=0.17.0 ; extra == 'rag'
Requires-Python: >=3.11
Provides-Extra: rag
